tripo/__init__.py
tripo/client.py
tripo/model.py
tripo-0.2.1.dist-info/METADATA
tripo-0.2.1.dist-info/WHEEL
tripo-0.2.1.dist-info/RECORD
