Metadata-Version: 2.4
Name: tripo
Version: 0.2.1
Summary: Tripo Python Client
Requires-Python: >=3.11
Requires-Dist: httpx>=0.27.2
Requires-Dist: pydantic>=2.9.2
